odoo/addons/fs_folder_webdav/README.rst
odoo/addons/fs_folder_webdav/__init__.py
odoo/addons/fs_folder_webdav/__manifest__.py
odoo/addons/fs_folder_webdav/i18n/fs_folder_webdav.pot
odoo/addons/fs_folder_webdav/i18n/it.po
odoo/addons/fs_folder_webdav/readme/CONFIGURE.md
odoo/addons/fs_folder_webdav/readme/CONTRIBUTORS.md
odoo/addons/fs_folder_webdav/readme/DESCRIPTION.md
odoo/addons/fs_folder_webdav/static/description/icon.png
odoo/addons/fs_folder_webdav/static/description/index.html
odoo/addons/fs_folder_webdav/static/src/fs_folder_webdav/fs_folder.esm.js
odoo_addon_fs_folder_webdav-18.0.1.0.0.3.dist-info/METADATA
odoo_addon_fs_folder_webdav-18.0.1.0.0.3.dist-info/WHEEL
odoo_addon_fs_folder_webdav-18.0.1.0.0.3.dist-info/top_level.txt
odoo_addon_fs_folder_webdav-18.0.1.0.0.3.dist-info/RECORD
