Metadata-Version: 2.1
Name: odoo-addon-fs_folder_webdav
Version: 18.0.1.0.0.3
Requires-Python: >=3.10
Requires-Dist: odoo-addon-fs_folder==18.0.*
Requires-Dist: odoo==18.0.*
Requires-Dist: webdav4[fsspec]
Summary: UI improvement when managing WebDAV folder
Home-page: https://github.com/OCA/storage
License: AGPL-3
Author: Odoo Community Association (OCA)
Author-email: support@odoo-community.org
Classifier: Programming Language :: Python
Classifier: Framework :: Odoo
Classifier: Framework :: Odoo :: 18.0
Classifier: License :: OSI Approved :: GNU Affero General Public License v3
